pmmif/__init__.py
pmmif/featherpmm.py
pmmif/pmm.py
pmmif/testpmm.py
pmmif/version.py
pmmif/data/hillstrom.pmm
pmmif/data/victorlo.pmm
pmmif/doc/Makefile
pmmif/doc/build/doctrees/data.doctree
pmmif/doc/build/doctrees/environment.pickle
pmmif/doc/build/doctrees/fields.doctree
pmmif/doc/build/doctrees/index.doctree
pmmif/doc/build/doctrees/overview.doctree
pmmif/doc/build/doctrees/toplevel.doctree
pmmif/doc/build/html/.buildinfo
pmmif/doc/build/html/data.html
pmmif/doc/build/html/fields.html
pmmif/doc/build/html/genindex.html
pmmif/doc/build/html/index.html
pmmif/doc/build/html/objects.inv
pmmif/doc/build/html/overview.html
pmmif/doc/build/html/search.html
pmmif/doc/build/html/searchindex.js
pmmif/doc/build/html/toplevel.html
pmmif/doc/build/html/_sources/data.txt
pmmif/doc/build/html/_sources/fields.txt
pmmif/doc/build/html/_sources/index.txt
pmmif/doc/build/html/_sources/overview.txt
pmmif/doc/build/html/_sources/toplevel.txt
pmmif/doc/build/html/_static/ajax-loader.gif
pmmif/doc/build/html/_static/basic.css
pmmif/doc/build/html/_static/classic.css
pmmif/doc/build/html/_static/comment-bright.png
pmmif/doc/build/html/_static/comment-close.png
pmmif/doc/build/html/_static/comment.png
pmmif/doc/build/html/_static/default.css
pmmif/doc/build/html/_static/doctools.js
pmmif/doc/build/html/_static/down-pressed.png
pmmif/doc/build/html/_static/down.png
pmmif/doc/build/html/_static/file.png
pmmif/doc/build/html/_static/jquery-3.1.0.js
pmmif/doc/build/html/_static/jquery.js
pmmif/doc/build/html/_static/minus.png
pmmif/doc/build/html/_static/plus.png
pmmif/doc/build/html/_static/pygments.css
pmmif/doc/build/html/_static/searchtools.js
pmmif/doc/build/html/_static/sidebar.js
pmmif/doc/build/html/_static/underscore-1.3.1.js
pmmif/doc/build/html/_static/underscore.js
pmmif/doc/build/html/_static/up-pressed.png
pmmif/doc/build/html/_static/up.png
pmmif/doc/build/html/_static/websupport.js
pmmif/doc/source/conf.py
pmmif/doc/source/data.txt
pmmif/doc/source/fields.txt
pmmif-0.1.11.dist-info/LICENSE.txt
pmmif-0.1.11.dist-info/METADATA
pmmif-0.1.11.dist-info/WHEEL
pmmif-0.1.11.dist-info/top_level.txt
pmmif-0.1.11.dist-info/RECORD
