Metadata-Version: 2.1
Name: pmmif
Version: 0.1.11
Summary: Predictive Modelling Metadata Interchange Format
Home-page: http://www.tdda.info
Author: Stochastic Solutions Limited
Author-email: info@StochasticSolutions.com
License: MIT
Download-URL: https://github.com/tdda/pmmif
Keywords: predictive modelling metadata
Platform: UNKNOWN
License-File: LICENSE.txt
Requires-Dist: numpy (>=1.9)
